markdown_sitegen/__init__.py
markdown_sitegen/cli.py
markdown_sitegen/web/base.html
markdown_sitegen/web/index.html
markdown_sitegen/web/post.html
markdown_sitegen-0.0.1.dist-info/METADATA
markdown_sitegen-0.0.1.dist-info/WHEEL
markdown_sitegen-0.0.1.dist-info/entry_points.txt
markdown_sitegen-0.0.1.dist-info/top_level.txt
markdown_sitegen-0.0.1.dist-info/RECORD
